meta_robyn_py-0.1.0.dist-info/licenses/LICENSE
robyn/__init__.py
robyn/allocator.py
robyn/checks.py
robyn/clusters.py
robyn/convergence.py
robyn/inputs.py
robyn/model.py
robyn/outputs.py
robyn/pareto.py
robyn/response.py
robyn/transformation.py
robyn/utils.py
meta_robyn_py-0.1.0.dist-info/METADATA
meta_robyn_py-0.1.0.dist-info/WHEEL
meta_robyn_py-0.1.0.dist-info/top_level.txt
meta_robyn_py-0.1.0.dist-info/RECORD
