Metadata-Version: 2.4
Name: meta-robyn-py
Version: 0.1.0
Summary: Python port of the Meta Robyn Marketing Mix Modeling (MMM) package
Author-email: Robyn Team <robyn@meta.com>
License: 
Project-URL: Homepage, https://github.com/facebookexperimental/Robyn
Project-URL: Bug Tracker, https://github.com/facebookexperimental/Robyn/issues
Keywords: marketing,mmm,econometrics,causal-inference,data-science
Classifier: Programming Language :: Python :: 3
Classifier: License :: OSI Approved :: MIT License
Classifier: Operating System :: OS Independent
Classifier: Intended Audience :: Science/Research
Classifier: Topic :: Scientific/Engineering :: Mathematics
Requires-Python: >=3.9
License-File: LICENSE
Requires-Dist: numpy>=1.24.0
Requires-Dist: pandas>=2.0.0
Requires-Dist: scipy>=1.10.0
Requires-Dist: scikit-learn>=1.2.0
Requires-Dist: prophet>=1.1.0
Requires-Dist: nevergrad>=1.0.0
Requires-Dist: matplotlib>=3.7.0
Requires-Dist: seaborn>=0.12.0
Requires-Dist: tqdm>=4.65.0
Provides-Extra: dev
Requires-Dist: pytest; extra == "dev"
Requires-Dist: black; extra == "dev"
Requires-Dist: flake8; extra == "dev"
Dynamic: license-file
